bspice/__init__.py
bspice/core.py
bspice/downloads.py
bspice-0.0.3.dist-info/LICENSE.txt
bspice-0.0.3.dist-info/METADATA
bspice-0.0.3.dist-info/WHEEL
bspice-0.0.3.dist-info/top_level.txt
bspice-0.0.3.dist-info/RECORD
