Metadata-Version: 2.1
Name: bspice
Version: 0.0.3
Summary: Working with SPICE kernels
Home-page: https://github.com/behrouzz/bspice
Author: Behrouz Safari
Author-email: behrouz.safari@gmail.com
License: MIT
Classifier: Programming Language :: Python :: 3
Classifier: License :: OSI Approved :: MIT License
Classifier: Operating System :: OS Independent
Requires-Python: >=3.6
License-File: LICENSE.txt
Requires-Dist: numpy
Requires-Dist: requests
Requires-Dist: spiceypy
